statsmodels/LICENSE.txt
statsmodels/__init__.py
statsmodels/_version.py
statsmodels/api.py
statsmodels/conftest.py
statsmodels/setup.cfg
statsmodels/base/__init__.py
statsmodels/base/_constraints.py
statsmodels/base/_parameter_inference.py
statsmodels/base/_penalized.py
statsmodels/base/_penalties.py
statsmodels/base/_screening.py
statsmodels/base/covtype.py
statsmodels/base/data.py
statsmodels/base/distributed_estimation.py
statsmodels/base/elastic_net.py
statsmodels/base/l1_cvxopt.py
statsmodels/base/l1_slsqp.py
statsmodels/base/l1_solvers_common.py
statsmodels/base/model.py
statsmodels/base/optimizer.py
statsmodels/base/transform.py
statsmodels/base/wrapper.py
statsmodels/base/tests/__init__.py
statsmodels/base/tests/test_data.py
statsmodels/base/tests/test_distributed_estimation.py
statsmodels/base/tests/test_generic_methods.py
statsmodels/base/tests/test_optimize.py
statsmodels/base/tests/test_penalized.py
statsmodels/base/tests/test_penalties.py
statsmodels/base/tests/test_predict.py
statsmodels/base/tests/test_screening.py
statsmodels/base/tests/test_shrink_pickle.py
statsmodels/base/tests/test_transform.py
statsmodels/compat/__init__.py
statsmodels/compat/numpy.py
statsmodels/compat/pandas.py
statsmodels/compat/platform.py
statsmodels/compat/python.py
statsmodels/compat/scipy.py
statsmodels/compat/tests/__init__.py
statsmodels/compat/tests/test_itercompat.py
statsmodels/compat/tests/test_scipy_compat.py
statsmodels/datasets/README.txt
statsmodels/datasets/__init__.py
statsmodels/datasets/template_data.py
statsmodels/datasets/utils.py
statsmodels/datasets/anes96/__init__.py
statsmodels/datasets/anes96/anes96.csv
statsmodels/datasets/anes96/data.py
statsmodels/datasets/cancer/__init__.py
statsmodels/datasets/cancer/cancer.csv
statsmodels/datasets/cancer/data.py
statsmodels/datasets/ccard/__init__.py
statsmodels/datasets/ccard/ccard.csv
statsmodels/datasets/ccard/data.py
statsmodels/datasets/china_smoking/__init__.py
statsmodels_dq-3.0.dist-info/LICENSE.txt
statsmodels_dq-3.0.dist-info/METADATA
statsmodels_dq-3.0.dist-info/WHEEL
statsmodels_dq-3.0.dist-info/top_level.txt
statsmodels_dq-3.0.dist-info/RECORD
