Metadata-Version: 2.1
Name: statsmodels-dq
Version: 3.0
Summary: Statistical computations and models for Python
Home-page: https://www.statsmodels.org/
Maintainer: Josef Perktold, Chad Fulton, Kerby Shedden
Maintainer-email: prateek.3211@gmail.com
License: BSD License
Project-URL: Bug Tracker, https://github.com/statsmodels/statsmodels/issues
Project-URL: Documentation, https://www.statsmodels.org/stable/index.html
Project-URL: Source Code, https://github.com/prateek3211/statsmodels
Platform: any
Classifier: Development Status :: 4 - Beta
Classifier: Environment :: Console
Classifier: Programming Language :: Cython
Classifier: Programming Language :: Python :: 2.7
Classifier: Programming Language :: Python :: 3.4
Classifier: Programming Language :: Python :: 3.5
Classifier: Programming Language :: Python :: 3.6
Classifier: Programming Language :: Python :: 3.7
Classifier: Operating System :: OS Independent
Classifier: Intended Audience :: End Users/Desktop
Classifier: Intended Audience :: Developers
Classifier: Intended Audience :: Science/Research
Classifier: Natural Language :: English
Classifier: License :: OSI Approved :: BSD License
Classifier: Topic :: Office/Business :: Financial
Classifier: Topic :: Scientific/Engineering
Requires-Dist: numpy (>=1.11)
Requires-Dist: scipy (>=0.18)
Requires-Dist: pandas (>=0.19)
Requires-Dist: patsy (>=0.4.0)
Provides-Extra: build
Requires-Dist: cython (>=0.24) ; extra == 'build'
Provides-Extra: develop
Requires-Dist: cython (>=0.24) ; extra == 'develop'
Provides-Extra: docs
Requires-Dist: sphinx ; extra == 'docs'
Requires-Dist: nbconvert ; extra == 'docs'
Requires-Dist: jupyter-client ; extra == 'docs'
Requires-Dist: ipykernel ; extra == 'docs'
Requires-Dist: matplotlib ; extra == 'docs'
Requires-Dist: nbformat ; extra == 'docs'
Requires-Dist: numpydoc ; extra == 'docs'
Requires-Dist: pandas-datareader ; extra == 'docs'
